[{"name": "p1", "id": "p151", "age": 51, "gender": "Male", "visit_details": [{"duration": 13, "visited_by_doc": "Dr.A", "problem": "Eye-checkup", "bill": 450}, {"duration": 13, "visited_by_doc": "Dr.A", "problem": "Bloodwork", "bill": 100}]}, {"name": "p2", "id": "p232", "age": 32, "gender": "Female", "visit_details": [{"duration": 13, "visited_by_doc": "Dr.B", "problem": "Dialysis", "bill": 400}]}, {"name": "p3", "id": "p340", "age": 40, "gender": "Female", "visit_details": [{"duration": 10, "visited_by_doc": "Dr.A", "problem": "Fracture", "bill": 350}]}, {"name": "p4", "id": "p454", "age": 54, "gender": "Male", "visit_details": [{"duration": 10, "visited_by_doc": "Dr.B", "problem": "Headache", "bill": 300}]}, {"name": "p5", "id": "p537", "age": 37, "gender": "Male", "visit_details": [{"duration": 11, "visited_by_doc": "Dr.A", "problem": "Fever", "bill": 200}]}]